{
  "generated_at": "2026-07-10T09:50:37.767450+00:00",
  "bankroll": 1000,
  "kelly_fraction": 0.25,
  "sports": [
    "soccer_fifa_world_cup"
  ],
  "thresholds": {
    "min_ev_pct": 2.0,
    "max_ev_pct": 15.0,
    "min_odds": 1.4,
    "max_odds": 4.0,
    "min_books": 4
  },
  "requests_remaining": "444",
  "n_events_considered": 13,
  "n_picks": 0,
  "performance": {
    "settled_bets": 41,
    "win_rate_pct": 48.8,
    "roi_pct": 24.07,
    "clv_beat_pct": null
  },
  "picks": [],
  "candidates": [
    {
      "league": "FIFA World Cup",
      "sport_key": "soccer_fifa_world_cup",
      "home": "Argentina",
      "away": "Switzerland",
      "commence": "2026-07-12T01:00:00Z",
      "market": "h2h",
      "selection": "Switzerland",
      "best_odds": 6.4,
      "bookmaker": "smarkets",
      "fair_prob": 0.1598,
      "fair_odds": 6.257,
      "ev_pct": 2.29,
      "stake_pct": 0.11,
      "stake_amount": 1.06,
      "confidence": 0.8,
      "n_books": 41
    },
    {
      "league": "FIFA World Cup",
      "sport_key": "soccer_fifa_world_cup",
      "home": "Spain",
      "away": "Belgium",
      "commence": "2026-07-10T19:00:00Z",
      "market": "h2h",
      "selection": "Belgium",
      "best_odds": 6.2,
      "bookmaker": "unibet_fr",
      "fair_prob": 0.1631,
      "fair_odds": 6.132,
      "ev_pct": 1.1,
      "stake_pct": 0.05,
      "stake_amount": 0.53,
      "confidence": 0.8,
      "n_books": 41
    },
    {
      "league": "FIFA World Cup",
      "sport_key": "soccer_fifa_world_cup",
      "home": "Norway",
      "away": "England",
      "commence": "2026-07-11T21:00:00Z",
      "market": "h2h",
      "selection": "England",
      "best_odds": 1.94,
      "bookmaker": "smarkets",
      "fair_prob": 0.5187,
      "fair_odds": 1.928,
      "ev_pct": 0.62,
      "stake_pct": 0.17,
      "stake_amount": 1.65,
      "confidence": 0.8,
      "n_books": 41
    },
    {
      "league": "FIFA World Cup",
      "sport_key": "soccer_fifa_world_cup",
      "home": "Spain",
      "away": "Belgium",
      "commence": "2026-07-10T19:00:00Z",
      "market": "h2h",
      "selection": "Spain",
      "best_odds": 1.68,
      "bookmaker": "matchbook",
      "fair_prob": 0.5957,
      "fair_odds": 1.679,
      "ev_pct": 0.07,
      "stake_pct": 0.03,
      "stake_amount": 0.26,
      "confidence": 0.8,
      "n_books": 41
    }
  ],
  "staking": {
    "bankroll": 1000,
    "kelly_fraction": 0.25,
    "max_stake_pct": 2.5
  },
  "default_thresholds": {
    "min_ev_pct": 2.0,
    "max_ev_pct": 15.0,
    "min_odds": 1.4,
    "max_odds": 4.0,
    "min_books": 4
  },
  "notes": [
    "ratings.json chyba -> model preskoceny, pouziva sa cisty trh (OK pre MS).",
    "7 zapasov preskocenych (ostra kniha nepokryva vsetky vybery)."
  ]
}