{
  "generated_at": "2026-06-23T09:59:45.789962+00:00",
  "bankroll": 1000,
  "kelly_fraction": 0.25,
  "sports": [
    "soccer_fifa_world_cup"
  ],
  "thresholds": {
    "min_ev_pct": 2.0,
    "max_ev_pct": 15.0,
    "min_odds": 1.4,
    "max_odds": 4.0,
    "min_books": 4
  },
  "requests_remaining": "388",
  "n_events_considered": 65,
  "n_picks": 6,
  "performance": {
    "settled_bets": 10,
    "win_rate_pct": 50.0,
    "roi_pct": 5.06,
    "clv_beat_pct": null
  },
  "picks": [
    {
      "league": "FIFA World Cup",
      "sport_key": "soccer_fifa_world_cup",
      "home": "Czech Republic",
      "away": "Mexico",
      "commence": "2026-06-25T01:00:00Z",
      "market": "h2h",
      "selection": "Czech Republic",
      "best_odds": 4.0,
      "bookmaker": "unibet_nl",
      "fair_prob": 0.2637,
      "fair_odds": 3.792,
      "ev_pct": 5.47,
      "stake_pct": 0.46,
      "stake_amount": 4.56,
      "confidence": 0.8,
      "n_books": 42
    },
    {
      "league": "FIFA World Cup",
      "sport_key": "soccer_fifa_world_cup",
      "home": "Ecuador",
      "away": "Germany",
      "commence": "2026-06-25T20:00:00Z",
      "market": "h2h",
      "selection": "Ecuador",
      "best_odds": 4.0,
      "bookmaker": "smarkets",
      "fair_prob": 0.2612,
      "fair_odds": 3.829,
      "ev_pct": 4.48,
      "stake_pct": 0.37,
      "stake_amount": 3.73,
      "confidence": 0.8,
      "n_books": 41
    },
    {
      "league": "FIFA World Cup",
      "sport_key": "soccer_fifa_world_cup",
      "home": "Japan",
      "away": "Sweden",
      "commence": "2026-06-25T23:00:00Z",
      "market": "h2h",
      "selection": "Draw",
      "best_odds": 3.7,
      "bookmaker": "betfair_ex_eu",
      "fair_prob": 0.2817,
      "fair_odds": 3.55,
      "ev_pct": 4.23,
      "stake_pct": 0.39,
      "stake_amount": 3.91,
      "confidence": 0.8,
      "n_books": 41
    },
    {
      "league": "FIFA World Cup",
      "sport_key": "soccer_fifa_world_cup",
      "home": "Paraguay",
      "away": "Australia",
      "commence": "2026-06-26T02:00:00Z",
      "market": "h2h",
      "selection": "Draw",
      "best_odds": 2.33,
      "bookmaker": "unibet_se",
      "fair_prob": 0.4452,
      "fair_odds": 2.246,
      "ev_pct": 3.74,
      "stake_pct": 0.7,
      "stake_amount": 7.02,
      "confidence": 0.8,
      "n_books": 41
    },
    {
      "league": "FIFA World Cup",
      "sport_key": "soccer_fifa_world_cup",
      "home": "Bosnia & Herzegovina",
      "away": "Qatar",
      "commence": "2026-06-24T19:00:00Z",
      "market": "h2h",
      "selection": "Bosnia & Herzegovina",
      "best_odds": 1.45,
      "bookmaker": "gtbets",
      "fair_prob": 0.7076,
      "fair_odds": 1.413,
      "ev_pct": 2.61,
      "stake_pct": 1.45,
      "stake_amount": 14.48,
      "confidence": 0.8,
      "n_books": 42
    },
    {
      "league": "FIFA World Cup",
      "sport_key": "soccer_fifa_world_cup",
      "home": "Switzerland",
      "away": "Canada",
      "commence": "2026-06-24T19:00:00Z",
      "market": "h2h",
      "selection": "Draw",
      "best_odds": 3.2,
      "bookmaker": "betfred_uk",
      "fair_prob": 0.3204,
      "fair_odds": 3.121,
      "ev_pct": 2.53,
      "stake_pct": 0.29,
      "stake_amount": 2.87,
      "confidence": 0.8,
      "n_books": 42
    }
  ],
  "candidates": [
    {
      "league": "FIFA World Cup",
      "sport_key": "soccer_fifa_world_cup",
      "home": "South Africa",
      "away": "South Korea",
      "commence": "2026-06-25T01:00:00Z",
      "market": "h2h",
      "selection": "South Africa",
      "best_odds": 6.0,
      "bookmaker": "unibet_nl",
      "fair_prob": 0.1841,
      "fair_odds": 5.433,
      "ev_pct": 10.44,
      "stake_pct": 0.52,
      "stake_amount": 5.22,
      "confidence": 0.8,
      "n_books": 41
    },
    {
      "league": "FIFA World Cup",
      "sport_key": "soccer_fifa_world_cup",
      "home": "Czech Republic",
      "away": "Mexico",
      "commence": "2026-06-25T01:00:00Z",
      "market": "h2h",
      "selection": "Czech Republic",
      "best_odds": 4.0,
      "bookmaker": "unibet_nl",
      "fair_prob": 0.2637,
      "fair_odds": 3.792,
      "ev_pct": 5.47,
      "stake_pct": 0.46,
      "stake_amount": 4.56,
      "confidence": 0.8,
      "n_books": 42
    },
    {
      "league": "FIFA World Cup",
      "sport_key": "soccer_fifa_world_cup",
      "home": "Ecuador",
      "away": "Germany",
      "commence": "2026-06-25T20:00:00Z",
      "market": "h2h",
      "selection": "Ecuador",
      "best_odds": 4.0,
      "bookmaker": "smarkets",
      "fair_prob": 0.2612,
      "fair_odds": 3.829,
      "ev_pct": 4.48,
      "stake_pct": 0.37,
      "stake_amount": 3.73,
      "confidence": 0.8,
      "n_books": 41
    },
    {
      "league": "FIFA World Cup",
      "sport_key": "soccer_fifa_world_cup",
      "home": "Japan",
      "away": "Sweden",
      "commence": "2026-06-25T23:00:00Z",
      "market": "h2h",
      "selection": "Draw",
      "best_odds": 3.7,
      "bookmaker": "betfair_ex_eu",
      "fair_prob": 0.2817,
      "fair_odds": 3.55,
      "ev_pct": 4.23,
      "stake_pct": 0.39,
      "stake_amount": 3.91,
      "confidence": 0.8,
      "n_books": 41
    },
    {
      "league": "FIFA World Cup",
      "sport_key": "soccer_fifa_world_cup",
      "home": "Paraguay",
      "away": "Australia",
      "commence": "2026-06-26T02:00:00Z",
      "market": "h2h",
      "selection": "Draw",
      "best_odds": 2.33,
      "bookmaker": "unibet_se",
      "fair_prob": 0.4452,
      "fair_odds": 2.246,
      "ev_pct": 3.74,
      "stake_pct": 0.7,
      "stake_amount": 7.02,
      "confidence": 0.8,
      "n_books": 41
    },
    {
      "league": "FIFA World Cup",
      "sport_key": "soccer_fifa_world_cup",
      "home": "Morocco",
      "away": "Haiti",
      "commence": "2026-06-24T22:00:00Z",
      "market": "h2h",
      "selection": "Morocco",
      "best_odds": 1.23,
      "bookmaker": "gtbets",
      "fair_prob": 0.8345,
      "fair_odds": 1.198,
      "ev_pct": 2.64,
      "stake_pct": 2.5,
      "stake_amount": 25.0,
      "confidence": 0.8,
      "n_books": 42
    },
    {
      "league": "FIFA World Cup",
      "sport_key": "soccer_fifa_world_cup",
      "home": "Bosnia & Herzegovina",
      "away": "Qatar",
      "commence": "2026-06-24T19:00:00Z",
      "market": "h2h",
      "selection": "Bosnia & Herzegovina",
      "best_odds": 1.45,
      "bookmaker": "gtbets",
      "fair_prob": 0.7076,
      "fair_odds": 1.413,
      "ev_pct": 2.61,
      "stake_pct": 1.45,
      "stake_amount": 14.48,
      "confidence": 0.8,
      "n_books": 42
    },
    {
      "league": "FIFA World Cup",
      "sport_key": "soccer_fifa_world_cup",
      "home": "Switzerland",
      "away": "Canada",
      "commence": "2026-06-24T19:00:00Z",
      "market": "h2h",
      "selection": "Draw",
      "best_odds": 3.2,
      "bookmaker": "betfred_uk",
      "fair_prob": 0.3204,
      "fair_odds": 3.121,
      "ev_pct": 2.53,
      "stake_pct": 0.29,
      "stake_amount": 2.87,
      "confidence": 0.8,
      "n_books": 42
    },
    {
      "league": "FIFA World Cup",
      "sport_key": "soccer_fifa_world_cup",
      "home": "England",
      "away": "Ghana",
      "commence": "2026-06-23T20:00:00Z",
      "market": "h2h",
      "selection": "Draw",
      "best_odds": 8.0,
      "bookmaker": "unibet_nl",
      "fair_prob": 0.128,
      "fair_odds": 7.81,
      "ev_pct": 2.43,
      "stake_pct": 0.09,
      "stake_amount": 0.87,
      "confidence": 0.8,
      "n_books": 42
    },
    {
      "league": "FIFA World Cup",
      "sport_key": "soccer_fifa_world_cup",
      "home": "Portugal",
      "away": "Uzbekistan",
      "commence": "2026-06-23T17:00:00Z",
      "market": "h2h",
      "selection": "Portugal",
      "best_odds": 1.19,
      "bookmaker": "onexbet",
      "fair_prob": 0.8525,
      "fair_odds": 1.173,
      "ev_pct": 1.44,
      "stake_pct": 1.9,
      "stake_amount": 18.97,
      "confidence": 0.8,
      "n_books": 42
    },
    {
      "league": "FIFA World Cup",
      "sport_key": "soccer_fifa_world_cup",
      "home": "Turkey",
      "away": "USA",
      "commence": "2026-06-26T02:00:00Z",
      "market": "h2h",
      "selection": "Turkey",
      "best_odds": 3.75,
      "bookmaker": "betfred_uk",
      "fair_prob": 0.2703,
      "fair_odds": 3.7,
      "ev_pct": 1.36,
      "stake_pct": 0.12,
      "stake_amount": 1.24,
      "confidence": 0.8,
      "n_books": 41
    },
    {
      "league": "FIFA World Cup",
      "sport_key": "soccer_fifa_world_cup",
      "home": "Ecuador",
      "away": "Germany",
      "commence": "2026-06-25T20:00:00Z",
      "market": "h2h",
      "selection": "Germany",
      "best_odds": 2.0,
      "bookmaker": "gtbets",
      "fair_prob": 0.5056,
      "fair_odds": 1.978,
      "ev_pct": 1.12,
      "stake_pct": 0.28,
      "stake_amount": 2.8,
      "confidence": 0.8,
      "n_books": 41
    },
    {
      "league": "FIFA World Cup",
      "sport_key": "soccer_fifa_world_cup",
      "home": "Bosnia & Herzegovina",
      "away": "Qatar",
      "commence": "2026-06-24T19:00:00Z",
      "market": "totals",
      "selection": "Over 3.0",
      "best_odds": 2.07,
      "bookmaker": "betonlineag",
      "fair_prob": 0.4881,
      "fair_odds": 2.049,
      "ev_pct": 1.04,
      "stake_pct": 0.24,
      "stake_amount": 2.42,
      "confidence": 0.55,
      "n_books": 4
    },
    {
      "league": "FIFA World Cup",
      "sport_key": "soccer_fifa_world_cup",
      "home": "Japan",
      "away": "Sweden",
      "commence": "2026-06-25T23:00:00Z",
      "market": "h2h",
      "selection": "Japan",
      "best_odds": 2.01,
      "bookmaker": "onexbet",
      "fair_prob": 0.5026,
      "fair_odds": 1.99,
      "ev_pct": 1.02,
      "stake_pct": 0.25,
      "stake_amount": 2.52,
      "confidence": 0.8,
      "n_books": 41
    },
    {
      "league": "FIFA World Cup",
      "sport_key": "soccer_fifa_world_cup",
      "home": "Panama",
      "away": "Croatia",
      "commence": "2026-06-23T23:00:00Z",
      "market": "h2h",
      "selection": "Croatia",
      "best_odds": 1.54,
      "bookmaker": "onexbet",
      "fair_prob": 0.6531,
      "fair_odds": 1.531,
      "ev_pct": 0.58,
      "stake_pct": 0.27,
      "stake_amount": 2.69,
      "confidence": 0.8,
      "n_books": 42
    },
    {
      "league": "FIFA World Cup",
      "sport_key": "soccer_fifa_world_cup",
      "home": "Colombia",
      "away": "DR Congo",
      "commence": "2026-06-24T02:00:00Z",
      "market": "h2h",
      "selection": "DR Congo",
      "best_odds": 7.4,
      "bookmaker": "betfair_ex_eu",
      "fair_prob": 0.1358,
      "fair_odds": 7.363,
      "ev_pct": 0.5,
      "stake_pct": 0.02,
      "stake_amount": 0.2,
      "confidence": 0.8,
      "n_books": 40
    },
    {
      "league": "FIFA World Cup",
      "sport_key": "soccer_fifa_world_cup",
      "home": "Curaçao",
      "away": "Ivory Coast",
      "commence": "2026-06-25T20:00:00Z",
      "market": "h2h",
      "selection": "Ivory Coast",
      "best_odds": 1.18,
      "bookmaker": "coolbet",
      "fair_prob": 0.8506,
      "fair_odds": 1.176,
      "ev_pct": 0.37,
      "stake_pct": 0.51,
      "stake_amount": 5.11,
      "confidence": 0.8,
      "n_books": 41
    },
    {
      "league": "FIFA World Cup",
      "sport_key": "soccer_fifa_world_cup",
      "home": "Tunisia",
      "away": "Netherlands",
      "commence": "2026-06-25T23:00:00Z",
      "market": "h2h",
      "selection": "Netherlands",
      "best_odds": 1.16,
      "bookmaker": "gtbets",
      "fair_prob": 0.8653,
      "fair_odds": 1.156,
      "ev_pct": 0.37,
      "stake_pct": 0.58,
      "stake_amount": 5.8,
      "confidence": 0.8,
      "n_books": 40
    },
    {
      "league": "FIFA World Cup",
      "sport_key": "soccer_fifa_world_cup",
      "home": "Colombia",
      "away": "DR Congo",
      "commence": "2026-06-24T02:00:00Z",
      "market": "h2h",
      "selection": "Colombia",
      "best_odds": 1.59,
      "bookmaker": "betfair_ex_eu",
      "fair_prob": 0.6309,
      "fair_odds": 1.585,
      "ev_pct": 0.31,
      "stake_pct": 0.13,
      "stake_amount": 1.33,
      "confidence": 0.8,
      "n_books": 40
    },
    {
      "league": "FIFA World Cup",
      "sport_key": "soccer_fifa_world_cup",
      "home": "Paraguay",
      "away": "Australia",
      "commence": "2026-06-26T02:00:00Z",
      "market": "h2h",
      "selection": "Australia",
      "best_odds": 4.25,
      "bookmaker": "onexbet",
      "fair_prob": 0.2357,
      "fair_odds": 4.243,
      "ev_pct": 0.16,
      "stake_pct": 0.01,
      "stake_amount": 0.12,
      "confidence": 0.8,
      "n_books": 41
    },
    {
      "league": "FIFA World Cup",
      "sport_key": "soccer_fifa_world_cup",
      "home": "Turkey",
      "away": "USA",
      "commence": "2026-06-26T02:00:00Z",
      "market": "h2h",
      "selection": "USA",
      "best_odds": 2.0,
      "bookmaker": "smarkets",
      "fair_prob": 0.5001,
      "fair_odds": 1.999,
      "ev_pct": 0.03,
      "stake_pct": 0.01,
      "stake_amount": 0.07,
      "confidence": 0.8,
      "n_books": 41
    }
  ],
  "staking": {
    "bankroll": 1000,
    "kelly_fraction": 0.25,
    "max_stake_pct": 2.5
  },
  "default_thresholds": {
    "min_ev_pct": 2.0,
    "max_ev_pct": 15.0,
    "min_odds": 1.4,
    "max_odds": 4.0,
    "min_books": 4
  },
  "notes": [
    "ratings.json chyba -> model preskoceny, pouziva sa cisty trh (OK pre MS).",
    "33 zapasov preskocenych (ostra kniha nepokryva vsetky vybery)."
  ]
}